{
  "updated_at": "2026-06-26T14:54:03.627577+00:00",
  "open_count": 1,
  "open_positions": [
    {
      "id": "USD/CHF-dtp-1782485643",
      "pair": "USD/CHF",
      "method": "dtp",
      "direction": "long",
      "entry_type": "dtp_long",
      "entry_time": "2026-06-26T14:54:03.627577",
      "entry_price": 0.8084700107574463,
      "stop_loss": 0.8057534199357033,
      "take_profit": 0.8166197832226754,
      "score": 100,
      "last_check_time": "2026-06-26T14:54:03.627577"
    }
  ],
  "history_count": 0,
  "recent_trades": [],
  "stats": {
    "trades": 0,
    "wins": 0,
    "losses": 0,
    "win_rate": 0.0,
    "total_r": 0.0,
    "expectancy_r": 0.0,
    "profit_factor": 0.0,
    "by_method": {}
  }
}