{
  "updated_at": "2026-05-29T16:31:32.468311+00:00",
  "open_count": 2,
  "open_positions": [
    {
      "id": "GBP/JPY-orz-1780072292",
      "pair": "GBP/JPY",
      "method": "orz",
      "direction": "short",
      "entry_type": "range_reversal",
      "entry_time": "2026-05-29T16:31:32.468311",
      "entry_price": 214.4290008544922,
      "stop_loss": 215.03521239913138,
      "take_profit": 210.5500030517578,
      "score": 79,
      "last_check_time": "2026-05-29T16:31:32.468311"
    },
    {
      "id": "USD/JPY-dtp-1780072292",
      "pair": "USD/JPY",
      "method": "dtp",
      "direction": "long",
      "entry_type": "dtp_long",
      "entry_time": "2026-05-29T16:31:32.468311",
      "entry_price": 159.23699951171875,
      "stop_loss": 158.93090634155274,
      "take_profit": 160.15527902221677,
      "score": 100,
      "last_check_time": "2026-05-29T16:31:32.468311"
    }
  ],
  "history_count": 0,
  "recent_trades": [],
  "stats": {
    "trades": 0,
    "wins": 0,
    "losses": 0,
    "win_rate": 0.0,
    "total_r": 0.0,
    "expectancy_r": 0.0,
    "profit_factor": 0.0,
    "by_method": {}
  }
}